PyColorPalette/Kmeans.py
PyColorPalette/__init__.py
PyColorPalette/core.py
PyColorPalette-1.2.2.dist-info/METADATA
PyColorPalette-1.2.2.dist-info/RECORD
PyColorPalette-1.2.2.dist-info/WHEEL
PyColorPalette-1.2.2.dist-info/top_level.txt
