Metadata-Version: 2.1
Name: PyColorPalette
Version: 1.2.2
Summary: UNKNOWN
Home-page: https://github.com/Dilan1020/PyColorPalette
Author: Dilan Ozkaynak
Author-email: DilanJames10@gmail.com
License: UNKNOWN
Platform: UNKNOWN
